load_stock_price_into_bigquery/__init__.py
load_stock_price_into_bigquery/main.py
load_stock_price_into_bigquery/sp500_symbols.py
load_stock_price_into_bigquery-0.1.10.dist-info/entry_points.txt
load_stock_price_into_bigquery-0.1.10.dist-info/WHEEL
load_stock_price_into_bigquery-0.1.10.dist-info/METADATA
load_stock_price_into_bigquery-0.1.10.dist-info/RECORD
