Metadata-Version: 2.1
Name: load-stock-price-into-bigquery
Version: 0.1.10
Summary: 
Author: tyama711
Author-email: tyama711@gmail.com
Requires-Python: >=3.9,<3.11
Classifier: Programming Language :: Python :: 3
Classifier: Programming Language :: Python :: 3.10
Classifier: Programming Language :: Python :: 3.9
Requires-Dist: google-cloud-bigquery (>=2.32.0,<3.0.0)
Requires-Dist: numpy (>=1.22.2,<2.0.0)
Requires-Dist: pandas (>=1.4.0,<2.0.0)
Requires-Dist: pandas-datareader (>=0.10.0,<0.11.0)
